afip/__init__.py
afip/afip.py
afip/data/cacert.pem
afip/electronic_billing.py
afip/register_inscription_proof.py
afip/register_scope_ten.py
afip/register_scope_thirteen.py
afip/web_service.py
afip_py-1.1.2.dist-info/LICENSE.txt
afip_py-1.1.2.dist-info/METADATA
afip_py-1.1.2.dist-info/WHEEL
afip_py-1.1.2.dist-info/RECORD
